kiss_headers/__init__.py
kiss_headers/api.py
kiss_headers/builder.py
kiss_headers/models.py
kiss_headers/py.typed
kiss_headers/serializer.py
kiss_headers/structures.py
kiss_headers/utils.py
kiss_headers/version.py
kiss_headers-2.5.0.dist-info/METADATA
kiss_headers-2.5.0.dist-info/WHEEL
kiss_headers-2.5.0.dist-info/licenses/LICENSE
kiss_headers-2.5.0.dist-info/RECORD
