Metadata-Version: 2.4
Name: kiss-headers
Version: 2.5.0
Summary: Object-oriented HTTP and IMAP (structured) headers.
Project-URL: Documentation, https://jawah.github.io/kiss-headers
Project-URL: Code, https://github.com/jawah/kiss-headers
Project-URL: Issue tracker, https://github.com/jawah/kiss-headers/issues
Author-email: "Ahmed R. TAHRI" <tahri.ahmed@proton.me>
Maintainer-email: "Ahmed R. TAHRI" <tahri.ahmed@proton.me>
License-Expression: MIT
License-File: LICENSE
Keywords: header,headers,http,https,imap,imap4,mail,text
Classifier: Development Status :: 5 - Production/Stable
Classifier: Environment :: Web Environment
Classifier: Intended Audience :: Developers
Classifier: License :: OSI Approved :: MIT License
Classifier: Operating System :: OS Independent
Classifier: Programming Language :: Python :: 3
Classifier: Programming Language :: Python :: 3 :: Only
Classifier: Programming Language :: Python :: 3.7
Classifier: Programming Language :: Python :: 3.8
Classifier: Programming Language :: Python :: 3.9
Classifier: Programming Language :: Python :: 3.10
Classifier: Programming Language :: Python :: 3.11
Classifier: Programming Language :: Python :: 3.12
Classifier: Programming Language :: Python :: 3.13
Classifier: Programming Language :: Python :: Implementation :: PyPy
Classifier: Topic :: Communications :: Email
Classifier: Topic :: Internet :: WWW/HTTP
Classifier: Topic :: Internet :: WWW/HTTP :: Dynamic Content :: Content Management System
Classifier: Topic :: Software Development :: Libraries :: Python Modules
Classifier: Topic :: Utilities
Requires-Python: >=3.7
